LICENSE
README.md
setup.py
mplutils/__init__.py
mplutils/custom_cmap.py
mplutils/multi_pcolor.py
mplutils.egg-info/PKG-INFO
mplutils.egg-info/SOURCES.txt
mplutils.egg-info/dependency_links.txt
mplutils.egg-info/requires.txt
mplutils.egg-info/top_level.txt